aidapy/__init__.py
aidapy/aidafunc/__init__.py
aidapy/aidafunc/event_search.py
aidapy/aidafunc/load_data.py
aidapy/aidafunc/set_load_config.py
aidapy/aidafunc/tests/test_event_search.py
aidapy/aidafunc/tests/test_get_info.py
aidapy/aidafunc/tests/test_load_data.py
aidapy/aidaxr/__init__.py
aidapy/aidaxr/graphical.py
aidapy/aidaxr/process.py
aidapy/aidaxr/statistics.py
aidapy/aidaxr/tools.py
aidapy/aidaxr/vdf.py
aidapy/aidaxr/xevents.py
aidapy/aidaxr/tests/__init__.py
aidapy/aidaxr/tests/test_graphical.py
aidapy/aidaxr/tests/test_process.py
aidapy/aidaxr/tests/test_statistics.py
aidapy/aidaxr/tests/test_vdf_mms.py
aidapy/aidaxr/tests/test_xevents.py
aidapy/data/__init__.py
aidapy/data/mission/__init__.py
aidapy/data/mission/base_mission.py
aidapy/data/mission/cluster.py
aidapy/data/mission/mission.py
aidapy/data/mission/mms.py
aidapy/data/mission/modified_cluster.py
aidapy/data/mission/omni.py
aidapy/data/mission/mission_settings/__init__.py
aidapy/data/mission/mission_settings/cluster.json
aidapy/data/mission/mission_settings/mms.json
aidapy/data/mission/mission_settings/omni.json
aidapy/data/mission/mission_settings/settings.py
aidapy/data/mission/tests/__init__.py
aidapy/data/mission/tests/test_mission.py
aidapy/ml/__init__.py
aidapy/ml/gmm.py
aidapy/ml/mlp.py
aidapy/ml/preprocess.py
aidapy/ml/lstm/model.py
aidapy/ml/tests/__init__.py
aidapy/ml/tests/test_mlp.py
aidapy/ml/tests/test_preprocess.py
aidapy/tests/load_test_vdf_mms.py
aidapy/tests/save_xr_no_attrs.py
aidapy/tests/test_load_mission.py
aidapy/tests/test_vdf_mms.py
aidapy/tools/__init__.py
aidapy/tools/sitl_parsing.py
aidapy/tools/sitl_parsing_tool.py
aidapy/tools/vdf_plot.py
aidapy/tools/vdf_utils.py
aidapy/tools/tests/test_sitl_parsing.py
aidapy/tools/tests/test_vdf_utils.py
aidapy/tools/tests/data/2017-07-31_072433.txt
aidapy/tools/tests/data/formated/2017-07-31_072433.txt
aidapy/tools/tests/data/formated/formated.py
aidapy-0.0.4.dist-info/LICENSE.txt
aidapy-0.0.4.dist-info/METADATA
aidapy-0.0.4.dist-info/WHEEL
aidapy-0.0.4.dist-info/top_level.txt
aidapy-0.0.4.dist-info/RECORD
