Metadata-Version: 2.1
Name: aidapy
Version: 0.0.4
Summary: AI package for heliophysics
Home-page: https://gitlab.com/aidaspace/aidapy
Author: AIDA Consortium
Author-email: coordinator.aida@kuleuven.be
License: MIT
Platform: UNKNOWN
Requires-Python: >=3.5
Requires-Dist: numpy
Requires-Dist: matplotlib
Requires-Dist: xarray
Requires-Dist: astropy
Requires-Dist: heliopy (>=0.12.0)
Requires-Dist: heliopy-multid
Requires-Dist: sunpy
Requires-Dist: cdflib
Requires-Dist: requests
Requires-Dist: more-itertools
Requires-Dist: extension
Requires-Dist: bottleneck
Provides-Extra: doc
Requires-Dist: sphinx-rtd-theme ; extra == 'doc'
Requires-Dist: sphinx (>=1.4) ; extra == 'doc'
Requires-Dist: ipython ; extra == 'doc'
Requires-Dist: ipykernel ; extra == 'doc'
Requires-Dist: nbsphinx ; extra == 'doc'
Requires-Dist: sphinxcontrib-apidoc ; extra == 'doc'
Provides-Extra: ml
Requires-Dist: torch (>=1.3) ; extra == 'ml'
Requires-Dist: skorch ; extra == 'ml'
Requires-Dist: h5py ; extra == 'ml'
Requires-Dist: joblib ; extra == 'ml'
Provides-Extra: vdf_cub
Requires-Dist: tricubic ; extra == 'vdf_cub'
